task2/rom.sv
module rom #(
    parameter ADDRESS_WIDTH = 8,
              DATA_WIDTH = 8
)(
    input logic clk,
    input logic [ADDRESS_WIDTH - 1:0] addr,
    output logic [DATA_WIDTH - 1:0] dout
);

logic [DATA_WIDTH - 1:0] rom_array [2 ** ADDRESS_WIDTH - 1:0];

initial begin
    $display("Loading rom.");
    $readmemh("sinerom.mem", rom_array);
end;

always_ff @(posedge clk) dout <= rom_array[addr];

endmodule

task1/counter.sv
module counter #(
    parameter WIDTH = 8
)(
    // interface signals
    input   logic               clk,    // clock
    input   logic               rst,    // reset
    input   logic               en,     // counter enable
    input   logic [WIDTH - 1:0] incr,   // increment
    output  logic [WIDTH - 1:0] count   // count output
);

always_ff @ (posedge clk, posedge rst)
    if (rst) count <= {WIDTH{1'b0}};
    else count <= count + (en ? incr : {WIDTH{1'b0}});

endmodule

task1/sinegen.sv
module sinegen (
    input logic [7:0] incr,
    input logic rst,
    input logic en,
    input logic clk,
    output logic [7:0] dout
);

logic [7:0] addr;

counter addrCounter(
    .clk(clk),
    .rst(rst),
    .en(en),
    .incr(incr),
    .count(addr)
);

rom sineROM(
    .clk(clk),
    .addr(addr),
    .dout(dout)
);

endmodule

task1/sinegen.vcd
$version Generated by VerilatedVcd $end
$date Fri Oct 31 13:47:37 2025 $end
$timescale 1ps $end

 $scope module TOP $end
  $var wire  1 & clk $end
  $var wire  8 ' dout [7:0] $end
  $var wire  1 % en $end
  $var wire  8 # incr [7:0] $end
  $var wire  1 $ rst $end
  $scope module sinegen $end
   $var wire  8 ( addr [7:0] $end
   $var wire  1 & clk $end
   $var wire  8 ' dout [7:0] $end
   $var wire  1 % en $end
   $var wire  8 # incr [7:0] $end
   $var wire  1 $ rst $end
   $scope module addrCounter $end
    $var wire 32 ) WIDTH [31:0] $end
    $var wire  1 & clk $end
    $var wire  8 ( count [7:0] $end
    $var wire  1 % en $end
    $var wire  8 # incr [7:0] $end
    $var wire  1 $ rst $end
   $upscope $end
   $scope module sineROM $end
    $var wire 32 ) ADDRESS_WIDTH [31:0] $end
    $var wire 32 ) DATA_WIDTH [31:0] $end
    $var wire  8 ( addr [7:0] $end
    $var wire  1 & clk $end
    $var wire  8 ' dout [7:0] $end
   $upscope $end
  $upscope $end
 $upscope $end
$enddefinitions $end


#0
b00000001 #
1$
1%
1&
b00000000 '
b00000000 (
b00000000000000000000000000001000 )
#1
0&
#2
b00001100 #
0$
1&
b11111110 '
#3
0&
#4
1&
b00001100 (
#5
0&
#6
1&
b11111000 '
b00011000 (
#7
0&
#8
1&
b11101000 '
b00100100 (
#9
0&
#10
1&
b11001111 '
b00110000 (
#11
0&
#12
1&
b10101111 '
b00111100 (
#13
0&
#14
1&
b10001011 '
b01001000 (
#15
0&
#16
1&
b01100110 '
b01010100 (
#17
0&
#18
1&
b01000011 '
b01100000 (
#19
0&
#20
1&
b00100101 '
b01101100 (
#21
0&
#22
1&
b00001110 '
b01111000 (
#23
0&
#24
1&
b00000010 '
b10000100 (
#25
0&
#26
1&
b00000000 '
b10010000 (
#27
0&
#28
1&
b00001001 '
b10011100 (
#29
0&
#30
1&
b00011100 '
b10101000 (
#31
0&
#32
1&
b00111000 '
b10110100 (
#33
0&
#34
1&
b01011010 '
b11000000 (
#35
0&
#36
1&
b01111111 '
b11001100 (
#37
0&
#38
1&
b10100011 '
b11011000 (
#39
0&
#40
1&
b11000101 '
b11100100 (
#41
0&
#42
1&
b11100001 '
b11110000 (
#43
0&
#44
1&
b11110100 '
b11111100 (
#45
0&
#46
1&
b11111101 '
b00001000 (
#47
0&
#48
1&
b11111011 '
b00010100 (
#49
0&
#50
1&
b11101111 '
b00100000 (
#51
0&
#52
1&
b11011000 '
b00101100 (
#53
0&
#54
1&
b10111010 '
b00111000 (
#55
0&
#56
1&
b10010111 '
b01000100 (
#57
0&
#58
1&
b01110010 '
b01010000 (
#59
0&
#60
1&
b01001110 '
b01011100 (
#61
0&
#62
1&
b00101110 '
b01101000 (
#63
0&
#64
1&
b00010101 '
b01110100 (
#65
0&
#66
1&
b00000101 '
b10000000 (
#67
0&
#68
1&
b00000000 '
b10001100 (
#69
0&
#70
1&
b00000101 '
b10011000 (
#71
0&
#72
1&
b00010101 '
b10100100 (
#73
0&
#74
1&
b00101110 '
b10110000 (
#75
0&
#76
1&
b01001110 '
b10111100 (
#77
0&
#78
1&
b01110010 '
b11001000 (
#79
0&
#80
1&
b10010111 '
b11010100 (
#81
0&
#82
1&
b10111010 '
b11100000 (
#83
0&
#84
1&
b11011000 '
b11101100 (
#85
0&
#86
1&
b11101111 '
b11111000 (
#87
0&
#88
1&
b11111011 '
b00000100 (
#89
0&
#90
1&
b11111101 '
b00010000 (
#91
0&
#92
1&
b11110100 '
b00011100 (
#93
0&
#94
1&
b11100001 '
b00101000 (
#95
0&
#96
1&
b11000101 '
b00110100 (
#97
0&
#98
1&
b10100011 '
b01000000 (
#99
0&
#100
1&
b01111110 '
b01001100 (
#101
0&
#102
1&
b01011010 '
b01011000 (
#103
0&
#104
1&
b00111000 '
b01100100 (
#105
0&
#106
1&
b00011100 '
b01110000 (
#107
0&
#108
1&
b00001001 '
b01111100 (
#109
0&
#110
1&
b00000000 '
b10001000 (
#111
0&
#112
1&
b00000010 '
b10010100 (
#113
0&
#114
1&
b00001110 '
b10100000 (
#115
0&
#116
1&
b00100101 '
b10101100 (
#117
0&
#118
1&
b01000011 '
b10111000 (
#119
0&
#120
1&
b01100110 '
b11000100 (
#121
0&
#122
1&
b10001011 '
b11010000 (
#123
0&
#124
1&
b10101111 '
b11011100 (
#125
0&
#126
1&
b11001111 '
b11101000 (
#127
0&
#128
1&
b11101000 '
b11110100 (
#129
0&
#130
1&
b11111000 '
b00000000 (
#131
0&
#132
1&
b11111110 '
b00001100 (
#133
0&
#134
1&
b11111000 '
b00011000 (
#135
0&
#136
1&
b11101000 '
b00100100 (
#137
0&
#138
1&
b11001111 '
b00110000 (
#139
0&
#140
1&
b10101111 '
b00111100 (
#141
0&
#142
1&
b10001011 '
b01001000 (
#143
0&
#144
1&
b01100110 '
b01010100 (
#145
0&
#146
1&
b01000011 '
b01100000 (
#147
0&
#148
1&
b00100101 '
b01101100 (
#149
0&
#150
1&
b00001110 '
b01111000 (
#151
0&
#152
1&
b00000010 '
b10000100 (
#153
0&
#154
1&
b00000000 '
b10010000 (
#155
0&
#156
1&
b00001001 '
b10011100 (
#157
0&
#158
1&
b00011100 '
b10101000 (
#159
0&
#160
1&
b00111000 '
b10110100 (
#161
0&
#162
1&
b01011010 '
b11000000 (
#163
0&
#164
1&
b01111111 '
b11001100 (
#165
0&
#166
1&
b10100011 '
b11011000 (
#167
0&
#168
1&
b11000101 '
b11100100 (
#169
0&
#170
1&
b11100001 '
b11110000 (
#171
0&
#172
1&
b11110100 '
b11111100 (
#173
0&
#174
1&
b11111101 '
b00001000 (
#175
0&
#176
1&
b11111011 '
b00010100 (
#177
0&
#178
1&
b11101111 '
b00100000 (
#179
0&
#180
1&
b11011000 '
b00101100 (
#181
0&
#182
1&
b10111010 '
b00111000 (
#183
0&
#184
1&
b10010111 '
b01000100 (
#185
0&
#186
1&
b01110010 '
b01010000 (
#187
0&
#188
1&
b01001110 '
b01011100 (
#189
0&
#190
1&
b00101110 '
b01101000 (
#191
0&
#192
1&
b00010101 '
b01110100 (
#193
0&
#194
1&
b00000101 '
b10000000 (
#195
0&
#196
1&
b00000000 '
b10001100 (
#197
0&
#198
1&
b00000101 '
b10011000 (
#199
0&
#200
1&
b00010101 '
b10100100 (
#201
0&
#202
1&
b00101110 '
b10110000 (
#203
0&
#204
1&
b01001110 '
b10111100 (
#205
0&
#206
1&
b01110010 '
b11001000 (
#207
0&
#208
1&
b10010111 '
b11010100 (
#209
0&
#210
1&
b10111010 '
b11100000 (
#211
0&
#212
1&
b11011000 '
b11101100 (
#213
0&
#214
1&
b11101111 '
b11111000 (
#215
0&
#216
1&
b11111011 '
b00000100 (
#217
0&
#218
1&
b11111101 '
b00010000 (
#219
0&
#220
1&
b11110100 '
b00011100 (
#221
0&
#222
1&
b11100001 '
b00101000 (
#223
0&
#224
1&
b11000101 '
b00110100 (
#225
0&
#226
1&
b10100011 '
b01000000 (
#227
0&
#228
1&
b01111110 '
b01001100 (
#229
0&
#230
1&
b01011010 '
b01011000 (
#231
0&
#232
1&
b00111000 '
b01100100 (
#233
0&
#234
1&
b00011100 '
b01110000 (
#235
0&
#236
1&
b00001001 '
b01111100 (
#237
0&
#238
1&
b00000000 '
b10001000 (
#239
0&
#240
1&
b00000010 '
b10010100 (
#241
0&
#242
1&
b00001110 '
b10100000 (
#243
0&
#244
1&
b00100101 '
b10101100 (
#245
0&
#246
1&
b01000011 '
b10111000 (
#247
0&
#248
1&
b01100110 '
b11000100 (
#249
0&
#250
1&
b10001011 '
b11010000 (
#251
0&
#252
1&
b10101111 '
b11011100 (
#253
0&
#254
1&
b11001111 '
b11101000 (
#255
0&
#256
1&
b11101000 '
b11110100 (
#257
0&
#258
1&
b11111000 '
b00000000 (
#259
0&
#260
1&
b11111110 '
b00001100 (
#261
0&
#262
1&
b11111000 '
b00011000 (
#263
0&
#264
1&
b11101000 '
b00100100 (
#265
0&
#266
1&
b11001111 '
b00110000 (
#267
0&
#268
1&
b10101111 '
b00111100 (
#269
0&
#270
1&
b10001011 '
b01001000 (
#271
0&
#272
1&
b01100110 '
b01010100 (
#273
0&
#274
1&
b01000011 '
b01100000 (
#275
0&
#276
1&
b00100101 '
b01101100 (
#277
0&
#278
1&
b00001110 '
b01111000 (
#279
0&
#280
1&
b00000010 '
b10000100 (
#281
0&
#282
1&
b00000000 '
b10010000 (
#283
0&
#284
1&
b00001001 '
b10011100 (
#285
0&
#286
1&
b00011100 '
b10101000 (
#287
0&
#288
1&
b00111000 '
b10110100 (
#289
0&
#290
1&
b01011010 '
b11000000 (
#291
0&
#292
1&
b01111111 '
b11001100 (
#293
0&
#294
1&
b10100011 '
b11011000 (
#295
0&
#296
1&
b11000101 '
b11100100 (
#297
0&
#298
1&
b11100001 '
b11110000 (
#299
0&
#300
1&
b11110100 '
b11111100 (
#301
0&
#302
1&
b11111101 '
b00001000 (
#303
0&
#304
1&
b11111011 '
b00010100 (
#305
0&
#306
1&
b11101111 '
b00100000 (
#307
0&
#308
1&
b11011000 '
b00101100 (
#309
0&
#310
1&
b10111010 '
b00111000 (
#311
0&
#312
1&
b10010111 '
b01000100 (
#313
0&
#314
1&
b01110010 '
b01010000 (
#315
0&
#316
1&
b01001110 '
b01011100 (
#317
0&
#318
1&
b00101110 '
b01101000 (
#319
0&
#320
1&
b00010101 '
b01110100 (
#321
0&
#322
1&
b00000101 '
b10000000 (
#323
0&
#324
b00001101 #
1&
b00000000 '
b10001100 (
#325
0&
#326
1&
b00000101 '
b10011001 (
#327
0&
#328
1&
b00010111 '
b10100110 (
#329
0&
#330
1&
b00110011 '
b10110011 (
#331
0&
#332
1&
b01010111 '
b11000000 (
#333
0&
#334
1&
b01111111 '
b11001101 (
#335
0&
#336
1&
b10100110 '
b11011010 (
#337
0&
#338
1&
b11001010 '
b11100111 (
#339
0&
#340
1&
b11100110 '
b11110100 (
#341
0&
#342
1&
b11111000 '
b00000001 (
#343
0&
#344
1&
b11111101 '
b00001110 (
#345
0&
#346
1&
b11110110 '
b00011011 (
#347
0&
#348
1&
b11100011 '
b00101000 (
#349
0&
#350
1&
b11000101 '
b00110101 (
#351
0&
#352
1&
b10100000 '
b01000010 (
#353
0&
#354
1&
b01111000 '
b01001111 (
#355
0&
#356
1&
b01010001 '
b01011100 (
#357
0&
#358
1&
b00101110 '
b01101001 (
#359
0&
#360
1&
b00010011 '
b01110110 (
#361
0&
#362
1&
b00000011 '
b10000011 (
#363
0&
#364
1&
b00000000 '
b10010000 (
#365
0&
#366
1&
b00001001 '
b10011101 (
#367
0&
#368
1&
b00011110 '
b10101010 (
#369
0&
#370
1&
b00111101 '
b10110111 (
#371
0&
#372
1&
b01100011 '
b11000100 (
#373
0&
#374
1&
b10001011 '
b11010001 (
#375
0&
#376
1&
b10110010 '
b11011110 (
#377
0&
#378
1&
b11010100 '
b11101011 (
#379
0&
#380
1&
b11101101 '
b11111000 (
#381
0&
#382
1&
b11111011 '
b00000101 (
#383
0&
#384
1&
b11111101 '
b00010010 (
#385
0&
#386
1&
b11110001 '
b00011111 (
#387
0&
#388
1&
b11011010 '
b00101100 (
#389
0&
#390
1&
b10111010 '
b00111001 (
#391
0&
#392
1&
b10010100 '
b01000110 (
#393
0&
#394
1&
b01101100 '
b01010011 (
#395
0&
#396
1&
b01000101 '
b01100000 (
#397
0&
#398
1&
b00100101 '
b01101101 (
#399
0&
#400
1&
b00001101 '
b01111010 (
#401
0&
#402
1&
b00000001 '
b10000111 (
#403
0&
#404
1&
b10010100 (
#405
0&
#406
1&
b00001110 '
b10100001 (
#407
0&
#408
1&
b00100111 '
b10101110 (
#409
0&
#410
1&
b01001000 '
b10111011 (
#411
0&
#412
1&
b01101111 '
b11001000 (
#413
0&
#414
1&
b10010111 '
b11010101 (
#415
0&
#416
1&
b10111101 '
b11100010 (
#417
0&
#418
1&
b11011101 '
b11101111 (
#419
0&
#420
1&
b11110011 '
b11111100 (
#421
0&
#422
1&
b11111101 '
b00001001 (
#423
0&
#424
1&
b11111010 '
b00010110 (
#425
0&
#426
1&
b11101011 '
b00100011 (
#427
0&
#428
1&
b11010001 '
b00110000 (
#429
0&
#430
1&
b10101111 '
b00111101 (
#431
0&
#432
1&
b10001000 '
b01001010 (
#433
0&
#434
1&
b01100000 '
b01010111 (
#435
0&
#436
1&
b00111011 '
b01100100 (
#437
0&
#438
1&
b00011100 '
b01110001 (
#439
0&
#440
1&
b00001000 '
b01111110 (
#441
0&
#442
1&
b00000000 '
b10001011 (
#443
0&
#444
1&
b00000100 '
b10011000 (
#445
0&
#446
1&
b00010101 '
b10100101 (
#447
0&
#448
1&
b00110000 '
b10110010 (
#449
0&
#450
1&
b01010100 '
b10111111 (
#451
0&
#452
1&
b01111011 '
b11001100 (
#453
0&
#454
1&
b10100011 '
b11011001 (
#455
0&
#456
1&
b11001000 '
b11100110 (
#457
0&
#458
1&
b11100101 '
b11110011 (
#459
0&
#460
1&
b11110111 '
b00000000 (
#461
0&
#462
1&
b11111110 '
b00001101 (
#463
0&
#464
1&
b11110111 '
b00011010 (
#465
0&
#466
1&
b11100101 '
b00100111 (
#467
0&
#468
1&
b11001000 '
b00110100 (
#469
0&
#470
1&
b10100011 '
b01000001 (
#471
0&
#472
1&
b01111011 '
b01001110 (
#473
0&
#474
1&
b01010100 '
b01011011 (
#475
0&
#476
1&
b00110000 '
b01101000 (
#477
0&
#478
1&
b00010101 '
b01110101 (
#479
0&
#480
1&
b00000100 '
b10000010 (
#481
0&
#482
1&
b00000000 '
b10001111 (
#483
0&
#484
1&
b00001000 '
b10011100 (
#485
0&
#486
1&
b00011100 '
b10101001 (
#487
0&
#488
1&
b00111011 '
b10110110 (
#489
0&
#490
1&
b01100000 '
b11000011 (
#491
0&
#492
1&
b10001000 '
b11010000 (
#493
0&
#494
1&
b10101111 '
b11011101 (
#495
0&
#496
1&
b11010001 '
b11101010 (
#497
0&
#498
1&
b11101011 '
b11110111 (
#499
0&
#500
1&
b11111010 '
b00000100 (
#501
0&
#502
1&
b11111101 '
b00010001 (
#503
0&
#504
1&
b11110011 '
b00011110 (
#505
0&
#506
1&
b11011101 '
b00101011 (
#507
0&
#508
1&
b10111101 '
b00111000 (
#509
0&
#510
1&
b10010111 '
b01000101 (
#511
0&
#512
1&
b01101111 '
b01010010 (
#513
0&
#514
1&
b01001000 '
b01011111 (
#515
0&
#516
1&
b00100111 '
b01101100 (
#517
0&
#518
1&
b00001110 '
b01111001 (
#519
0&
#520
1&
b00000001 '
b10000110 (
#521
0&
#522
1&
b10010011 (
#523
0&
#524
1&
b00001101 '
b10100000 (
#525
0&
#526
1&
b00100101 '
b10101101 (
#527
0&
#528
1&
b01000101 '
b10111010 (
#529
0&
#530
1&
b01101100 '
b11000111 (
#531
0&
#532
1&
b10010100 '
b11010100 (
#533
0&
#534
1&
b10111010 '
b11100001 (
#535
0&
#536
1&
b11011010 '
b11101110 (
#537
0&
#538
1&
b11110001 '
b11111011 (
#539
0&
#540
1&
b11111101 '
b00001000 (
#541
0&
#542
1&
b11111011 '
b00010101 (
#543
0&
#544
1&
b11101101 '
b00100010 (
#545
0&
#546
1&
b11010100 '
b00101111 (
#547
0&
#548
1&
b10110010 '
b00111100 (
#549
0&
#550
1&
b10001011 '
b01001001 (
#551
0&
#552
1&
b01100011 '
b01010110 (
#553
0&
#554
1&
b00111101 '
b01100011 (
#555
0&
#556
1&
b00011110 '
b01110000 (
#557
0&
#558
1&
b00001001 '
b01111101 (
#559
0&
#560
1&
b00000000 '
b10001010 (
#561
0&
#562
1&
b00000011 '
b10010111 (
#563
0&
#564
1&
b00010011 '
b10100100 (
#565
0&
#566
1&
b00101110 '
b10110001 (
#567
0&
#568
1&
b01010001 '
b10111110 (
#569
0&
#570
1&
b01111000 '
b11001011 (
#571
0&
#572
1&
b10100000 '
b11011000 (
#573
0&
#574
1&
b11000101 '
b11100101 (
#575
0&
#576
1&
b11100011 '
b11110010 (
#577
0&
#578
1&
b11110110 '
b11111111 (
#579
0&
#580
1&
b11111101 '
b00001100 (
#581
0&
#582
1&
b11111000 '
b00011001 (
#583
0&
#584
1&
b11100110 '
b00100110 (
#585
0&
#586
1&
b11001010 '
b00110011 (
#587
0&
#588
1&
b10100110 '
b01000000 (
#589
0&
#590
1&
b01111110 '
b01001101 (
#591
0&
#592
1&
b01010111 '
b01011010 (
#593
0&
#594
1&
b00110011 '
b01100111 (
#595
0&
#596
1&
b00010111 '
b01110100 (
#597
0&
#598
1&
b00000101 '
b10000001 (
#599
0&
#600
1&
b00000000 '
b10001110 (
#601
0&
#602
1&
b00000111 '
b10011011 (
#603
0&
#604
1&
b00011010 '
b10101000 (
#605
0&
#606
1&
b00111000 '
b10110101 (
#607
0&
#608
1&
b01011101 '
b11000010 (
#609
0&
#610
1&
b10000101 '
b11001111 (
#611
0&
#612
1&
b10101100 '
b11011100 (
#613
0&
#614
1&
b11001111 '
b11101001 (
#615
0&
#616
1&
b11101010 '
b11110110 (
#617
0&
#618
1&
b11111010 '
b00000011 (
#619
0&
#620
1&
b11111101 '
b00010000 (
#621
0&
#622
1&
b11110100 '
b00011101 (
#623
0&
#624
1&
b11011111 '
b00101010 (
#625
0&
#626
1&
b11000000 '
b00110111 (
#627
0&
#628
1&
b10011010 '
b01000100 (
#629
0&
#630
1&
b01110010 '
b01010001 (
#631
0&
#632
1&
b01001011 '
b01011110 (
#633
0&
#634
b00001110 #
1&
b00101001 '
b01101011 (
#635
0&
#636
1&
b00010000 '
b01111001 (
#637
0&
#638
1&
b00000001 '
b10000111 (
#639
0&
#640
1&
b10010101 (
#641
0&
#642
1&
b00010000 '
b10100011 (
#643
0&
#644
1&
b00101100 '
b10110001 (
#645
0&
#646
1&
b01010001 '
b10111111 (
#647
0&
#648
1&
b01111011 '
b11001101 (
#649
0&
#650
1&
b10100110 '
b11011011 (
#651
0&
#652
1&
b11001101 '
b11101001 (
#653
0&
#654
1&
b11101010 '
b11110111 (
#655
0&
#656
1&
b11111010 '
b00000101 (
#657
0&
#658
1&
b11111101 '
b00010011 (
#659
0&
#660
1&
b11110000 '
b00100001 (
#661
0&
#662
1&
b11010110 '
b00101111 (
#663
0&
#664
1&
b10110010 '
b00111101 (
#665
0&
#666
1&
b10001000 '
b01001011 (
#667
0&
#668
1&
b01011101 '
b01011001 (
#669
0&
#670
1&
b00110101 '
b01100111 (
#671
0&
#672
1&
b00010111 '
b01110101 (
#673
0&
#674
1&
b00000100 '
b10000011 (
#675
0&
#676
1&
b00000000 '
b10010001 (
#677
0&
#678
1&
b00001010 '
b10011111 (
#679
0&
#680
1&
b00100011 '
b10101101 (
#681
0&
#682
1&
b01000101 '
b10111011 (
#683
0&
#684
1&
b01101111 '
b11001001 (
#685
0&
#686
1&
b10011010 '
b11010111 (
#687
0&
#688
1&
b11000010 '
b11100101 (
#689
0&
#690
1&
b11100011 '
b11110011 (
#691
0&
#692
1&
b11110111 '
b00000001 (
#693
0&
#694
1&
b11111101 '
b00001111 (
#695
0&
#696
1&
b11110101 '
b00011101 (
#697
0&
#698
1&
b11011111 '
b00101011 (
#699
0&
#700
1&
b10111101 '
b00111001 (
#701
0&
#702
1&
b10010100 '
b01000111 (
#703
0&
#704
1&
b01101001 '
b01010101 (
#705
0&
#706
1&
b01000000 '
b01100011 (
#707
0&
#708
1&
b00011110 '
b01110001 (
#709
0&
#710
1&
b00001000 '
b01111111 (
#711
0&
#712
1&
b00000000 '
b10001101 (
#713
0&
#714
1&
b00000110 '
b10011011 (
#715
0&
#716
1&
b00011010 '
b10101001 (
#717
0&
#718
1&
b00111011 '
b10110111 (
#719
0&
#720
1&
b01100011 '
b11000101 (
#721
0&
#722
1&
b10001110 '
b11010011 (
#723
0&
#724
1&
b10111000 '
b11100001 (
#725
0&
#726
1&
b11011010 '
b11101111 (
#727
0&
#728
1&
b11110011 '
b11111101 (
#729
0&
#730
1&
b11111101 '
b00001011 (
#731
0&
#732
1&
b11111001 '
b00011001 (
#733
0&
#734
1&
b11100110 '
b00100111 (
#735
0&
#736
1&
b11001000 '
b00110101 (
#737
0&
#738
1&
b10100000 '
b01000011 (
#739
0&
#740
1&
b01110101 '
b01010001 (
#741
0&
#742
1&
b01001011 '
b01011111 (
#743
0&
#744
1&
b00100111 '
b01101101 (
#745
0&
#746
1&
b00001101 '
b01111011 (
#747
0&
#748
1&
b00000000 '
b10001001 (
#749
0&
#750
1&
b00000011 '
b10010111 (
#751
0&
#752
1&
b00010011 '
b10100101 (
#753
0&
#754
1&
b00110000 '
b10110011 (
#755
0&
#756
1&
b01010111 '
b11000001 (
#757
0&
#758
1&
b10000010 '
b11001111 (
#759
0&
#760
1&
b10101100 '
b11011101 (
#761
0&
#762
1&
b11010001 '
b11101011 (
#763
0&
#764
1&
b11101101 '
b11111001 (
#765
0&
#766
1&
b11111100 '
b00000111 (
#767
0&
#768
1&
b00010101 (
#769
0&
#770
1&
b11101101 '
b00100011 (
#771
0&
#772
1&
b11010001 '
b00110001 (
#773
0&
#774
1&
b10101100 '
b00111111 (
#775
0&
#776
1&
b10000010 '
b01001101 (
#777
0&
#778
1&
b01010111 '
b01011011 (
#779
0&
#780
1&
b00110000 '
b01101001 (
#781
0&
#782
1&
b00010011 '
b01110111 (
#783
0&
#784
1&
b00000011 '
b10000101 (
#785
0&
#786
1&
b00000000 '
b10010011 (
#787
0&
#788
1&
b00001101 '
b10100001 (
#789
0&
#790
1&
b00100111 '
b10101111 (
#791
0&
#792
1&
b01001011 '
b10111101 (
#793
0&
#794
1&
b01110101 '
b11001011 (
#795
0&
#796
1&
b10100000 '
b11011001 (
#797
0&
#798
1&
b11001000 '
b11100111 (
#799
0&
#800
1&
b11100110 '
b11110101 (
#801
0&
#802
1&
b11111001 '
b00000011 (
#803
0&
#804
1&
b11111101 '
b00010001 (
#805
0&
#806
1&
b11110011 '
b00011111 (
#807
0&
#808
1&
b11011010 '
b00101101 (
#809
0&
#810
1&
b10111000 '
b00111011 (
#811
0&
#812
1&
b10001110 '
b01001001 (
#813
0&
#814
1&
b01100011 '
b01010111 (
#815
0&
#816
1&
b00111011 '
b01100101 (
#817
0&
#818
1&
b00011010 '
b01110011 (
#819
0&
#820
1&
b00000110 '
b10000001 (
#821
0&
#822
1&
b00000000 '
b10001111 (
#823
0&
#824
1&
b00001000 '
b10011101 (
#825
0&
#826
1&
b00011110 '
b10101011 (
#827
0&
#828
1&
b01000000 '
b10111001 (
#829
0&
#830
1&
b01101001 '
b11000111 (
#831
0&
#832
1&
b10010100 '
b11010101 (
#833
0&
#834
1&
b10111101 '
b11100011 (
#835
0&
#836
1&
b11011111 '
b11110001 (
#837
0&
#838
1&
b11110101 '
b11111111 (
#839
0&
#840
1&
b11111101 '
b00001101 (
#841
0&
#842
1&
b11110111 '
b00011011 (
#843
0&
#844
1&
b11100011 '
b00101001 (
#845
0&
#846
1&
b11000010 '
b00110111 (
#847
0&
#848
1&
b10011010 '
b01000101 (
#849
0&
#850
1&
b01101111 '
b01010011 (
#851
0&
#852
1&
b01000101 '
b01100001 (
#853
0&
#854
1&
b00100011 '
b01101111 (
#855
0&
#856
1&
b00001010 '
b01111101 (
#857
0&
#858
1&
b00000000 '
b10001011 (
#859
0&
#860
1&
b00000100 '
b10011001 (
#861
0&
#862
1&
b00010111 '
b10100111 (
#863
0&
#864
1&
b00110101 '
b10110101 (
#865
0&
#866
1&
b01011101 '
b11000011 (
#867
0&
#868
1&
b10001000 '
b11010001 (
#869
0&
#870
1&
b10110010 '
b11011111 (
#871
0&
#872
1&
b11010110 '
b11101101 (
#873
0&
#874
1&
b11110000 '
b11111011 (
#875
0&
#876
1&
b11111101 '
b00001001 (
#877
0&
#878
1&
b11111010 '
b00010111 (
#879
0&
#880
1&
b11101010 '
b00100101 (
#881
0&
#882
1&
b11001101 '
b00110011 (
#883
0&
#884
1&
b10100110 '
b01000001 (
#885
0&
#886
1&
b01111011 '
b01001111 (
#887
0&
#888
1&
b01010001 '
b01011101 (
#889
0&
#890
1&
b00101100 '
b01101011 (
#891
0&
#892
1&
b00010000 '
b01111001 (
#893
0&
#894
1&
b00000001 '
b10000111 (
#895
0&
#896
1&
b10010101 (
#897
0&
#898
1&
b00010000 '
b10100011 (
#899
0&
#900
1&
b00101100 '
b10110001 (
#901
0&
#902
1&
b01010001 '
b10111111 (
#903
0&
#904
1&
b01111011 '
b11001101 (
#905
0&
#906
1&
b10100110 '
b11011011 (
#907
0&
#908
1&
b11001101 '
b11101001 (
#909
0&
#910
1&
b11101010 '
b11110111 (
#911
0&
#912
1&
b11111010 '
b00000101 (
#913
0&
#914
1&
b11111101 '
b00010011 (
#915
0&
#916
1&
b11110000 '
b00100001 (
#917
0&
#918
1&
b11010110 '
b00101111 (
#919
0&
#920
1&
b10110010 '
b00111101 (
#921
0&
#922
1&
b10001000 '
b01001011 (
#923
0&
#924
1&
b01011101 '
b01011001 (
#925
0&
#926
1&
b00110101 '
b01100111 (
#927
0&
#928
1&
b00010111 '
b01110101 (
#929
0&
#930
1&
b00000100 '
b10000011 (
#931
0&
#932
1&
b00000000 '
b10010001 (
#933
0&
#934
1&
b00001010 '
b10011111 (
#935
0&
#936
1&
b00100011 '
b10101101 (
#937
0&
#938
1&
b01000101 '
b10111011 (
#939
0&
#940
1&
b01101111 '
b11001001 (
#941
0&
#942
1&
b10011010 '
b11010111 (
#943
0&
#944
1&
b11000010 '
b11100101 (
#945
0&
#946
1&
b11100011 '
b11110011 (
#947
0&
#948
1&
b11110111 '
b00000001 (
#949
0&
#950
1&
b11111101 '
b00001111 (
#951
0&
#952
b00001111 #
1&
b11110101 '
b00011101 (
#953
0&
#954
1&
b11011111 '
b00101100 (
#955
0&
#956
1&
b10111010 '
b00111011 (
#957
0&
#958
1&
b10001110 '
b01001010 (
#959
0&
#960
1&
b01100000 '
b01011001 (
#961
0&
#962
1&
b00110101 '
b01101000 (
#963
0&
#964
1&
b00010101 '
b01110111 (
#965
0&
#966
1&
b00000011 '
b10000110 (
#967
0&
#968
1&
b00000001 '
b10010101 (
#969
0&
#970
1&
b00010000 '
b10100100 (
#971
0&
#972
1&
b00101110 '
b10110011 (
#973
0&
#974
1&
b01010111 '
b11000010 (
#975
0&
#976
1&
b10000101 '
b11010001 (
#977
0&
#978
1&
b10110010 '
b11100000 (
#979
0&
#980
1&
b11011000 '
b11101111 (
#981
0&
#982
1&
b11110011 '
b11111110 (
#983
0&
#984
1&
b11111101 '
b00001101 (
#985
0&
#986
1&
b11110111 '
b00011100 (
#987
0&
#988
1&
b11100001 '
b00101011 (
#989
0&
#990
1&
b10111101 '
b00111010 (
#991
0&
#992
1&
b10010001 '
b01001001 (
#993
0&
#994
1&
b01100011 '
b01011000 (
#995
0&
#996
1&
b00111000 '
b01100111 (
#997
0&
#998
1&
b00010111 '
b01110110 (
#999
0&
#1000
1&
b00000011 '
b10000101 (
#1001
0&
#1002
1&
b00000000 '
b10010100 (
#1003
0&
#1004
1&
b00001110 '
b10100011 (
#1005
0&
#1006
1&
b00101100 '
b10110010 (
#1007
0&
#1008
1&
b01010100 '
b11000001 (
#1009
0&
#1010
1&
b10000010 '
b11010000 (
#1011
0&
#1012
1&
b10101111 '
b11011111 (
#1013
0&
#1014
1&
b11010110 '
b11101110 (
#1015
0&
#1016
1&
b11110001 '
b11111101 (
#1017
0&
#1018
1&
b11111101 '
b00001100 (
#1019
0&
#1020
1&
b11111000 '
b00011011 (
#1021
0&
#1022
1&
b11100011 '
b00101010 (
#1023
0&
#1024
1&
b11000000 '
b00111001 (
#1025
0&
#1026
1&
b10010100 '
b01001000 (
#1027
0&
#1028
1&
b01100110 '
b01010111 (
#1029
0&
#1030
1&
b00111011 '
b01100110 (
#1031
0&
#1032
1&
b00011000 '
b01110101 (
#1033
0&
#1034
1&
b00000100 '
b10000100 (
#1035
0&
#1036
1&
b00000000 '
b10010011 (
#1037
0&
#1038
1&
b00001101 '
b10100010 (
#1039
0&
#1040
1&
b00101001 '
b10110001 (
#1041
0&
#1042
1&
b01010001 '
b11000000 (
#1043
0&
#1044
1&
b01111111 '
b11001111 (
#1045
0&
#1046
1&
b10101100 '
b11011110 (
#1047
0&
#1048
1&
b11010100 '
b11101101 (
#1049
0&
#1050
1&
b11110000 '
b11111100 (
#1051
0&
#1052
1&
b11111101 '
b00001011 (
#1053
0&
#1054
1&
b11111001 '
b00011010 (
#1055
0&
#1056
1&
b11100101 '
b00101001 (
#1057
0&
